{"assets":{"424DF97B3B4C6D49E7C1543125824DB4":{"type":"texture","index":1,"assetRequest":{"type":"slide","state":"contents","slide":"none"},"url":{"native":"assets\/FD95C84C-3834-4DF2-BDF7-56BA97A3BD8D.pdf"},"width":1920,"height":1080},"D207410D0EE731715E667FC4EEB89E03":{"type":"texture","index":0,"assetRequest":{"type":"slide","state":"contents","slide":"none"},"url":{"native":"assets\/FD95C84C-3834-4DF2-BDF7-56BA97A3BD8D.pdf"},"width":1920,"height":1080}},"events":[{"effects":[{"beginTime":0,"baseLayer":{"animations":[],"initialState":{"affineTransform":[1,0,0,1,0,0],"masksToBounds":false,"rotation":0,"scale":1,"position":{"pointX":960,"pointY":540},"width":1920,"sublayerTransform":[1,0,0,0,0,1,0,0,0,0,1,0,0,0,0,1],"contentsRect":{"y":0,"x":0,"width":1,"height":1},"opacity":1,"edgeAntialiasingMask":251658240,"height":1080,"hidden":false,"anchorPoint":{"pointX":0.5,"pointY":0.5}},"objectID":"0","layers":[{"animations":[],"initialState":{"affineTransform":[1,0,0,1,0,0],"masksToBounds":false,"rotation":0,"scale":1,"position":{"pointX":960,"pointY":540},"width":1920,"sublayerTransform":[1,0,0,0,0,1,0,0,0,0,1,-0.00035007912466775983,0,0,0,1],"contentsRect":{"y":0,"x":0,"width":1,"height":1},"opacity":1,"edgeAntialiasingMask":251658240,"height":1080,"hidden":false,"anchorPoint":{"pointX":0.5,"pointY":0.5}},"layers":[{"animations":[],"layers":[],"texturedRectangle":{"isBackgroundTexture":false,"singleTextureOpacity":1,"textureType":0,"textBaseline":0,"textXHeight":0,"isVerticalText":false},"initialState":{"affineTransform":[1,0,0,1,0,0],"masksToBounds":false,"rotation":0,"scale":1,"position":{"pointX":960,"pointY":540},"width":1920,"sublayerTransform":[1,0,0,0,0,1,0,0,0,0,1,0,0,0,0,1],"contentsRect":{"y":0,"x":0,"width":1,"height":1},"opacity":1,"edgeAntialiasingMask":0,"height":1080,"hidden":false,"anchorPoint":{"pointX":0.5,"pointY":0.5}},"texture":"424DF97B3B4C6D49E7C1543125824DB4"},{"animations":[{"additive":false,"timeOffset":0,"beginTime":0,"from":{"scalar":false},"repeatCount":0,"fillMode":"both","duration":0.01,"autoreverses":false,"property":"hidden","to":{"scalar":true},"removedOnCompletion":false}],"layers":[],"texturedRectangle":{"isBackgroundTexture":false,"singleTextureOpacity":1,"textureType":0,"textBaseline":0,"textXHeight":0,"isVerticalText":false},"initialState":{"affineTransform":[1,0,0,1,0,0],"masksToBounds":false,"rotation":0,"scale":1,"position":{"pointX":960,"pointY":540},"width":1920,"sublayerTransform":[1,0,0,0,0,1,0,0,0,0,1,0,0,0,0,1],"contentsRect":{"y":0,"x":0,"width":1,"height":1},"opacity":1,"edgeAntialiasingMask":0,"height":1080,"hidden":false,"anchorPoint":{"pointX":0.5,"pointY":0.5}},"texture":"D207410D0EE731715E667FC4EEB89E03"}]}]},"effects":[],"duration":0.01,"type":"transition","attributes":{"direction":0},"name":"none","objectID":"0"}],"automaticPlay":false,"hyperlinks":[],"accessibility":[{"text":"<h1>hello world<h1>","targetRectangle":{"y":533.16799947619438,"x":1031.8387451171875,"width":113.91599999999994,"height":13.66400146484375}},{"text":"before_jsrb","targetRectangle":{"y":375.24919385795124,"x":1527.9644131850262,"width":124.51200000000017,"height":28.3038330078125}},{"text":"Opal ","targetRectangle":{"y":1023.8589935302734,"x":1368.950989440918,"width":46.473999999999933,"height":23.448867797851562}},{"text":"jsrb","targetRectangle":{"y":478.4595947265625,"x":1562.6524132080078,"width":55.135999999999967,"height":38.07177734375}},{"text":"Render Wrap","targetRectangle":{"y":88.831474304199219,"x":99,"width":511.7850004179777,"height":100.53440856933594}},{"text":"after_jsrb","targetRectangle":{"y":596.11421317939289,"x":1538.2004130892776,"width":104.03999999999996,"height":28.3038330078125}},{"text":"RenderWrap: 在html\/jsrb前后包上代码","targetRectangle":{"y":249.10140991210938,"x":165.97975158691406,"width":820.55999999999995,"height":67}},{"text":"before_html","targetRectangle":{"y":375.24919382539616,"x":1023.5007070556549,"width":131.5920000000001,"height":28.3038330078125}},{"text":"RenderWrap","targetRectangle":{"y":472.66027891635895,"x":1216.2945489883423,"width":246.92799999999988,"height":50.76800537109375}},{"text":"after_html","targetRectangle":{"y":596.11421320045793,"x":1033.7367071748645,"width":111.12000000000012,"height":28.3038330078125}},{"text":"JSRB","targetRectangle":{"y":1019.8589935302734,"x":1151.8223491821288,"width":67.41800000000012,"height":31.245819091796875}},{"text":"HTML","targetRectangle":{"y":945.97809600830078,"x":1149.4173491821289,"width":72.228000000000065,"height":31.245819091796875}},{"text":"puts ‘this is console log’","targetRectangle":{"y":532.6819988489151,"x":1519.409912109375,"width":140.62100000000009,"height":14.636001586914062}},{"text":"HTML","targetRectangle":{"y":942.97809600830078,"x":1754.3062343139648,"width":88.896000000000186,"height":38.07177734375}},{"text":"Page","targetRectangle":{"y":1020.9780960083008,"x":1760.8022343139648,"width":75.903999999999996,"height":38.07177734375}},{"text":"RenderWrap.html = “<h1>hello world<h1>”","targetRectangle":{"y":482.96033370494843,"x":150.33403015136719,"width":522.09900000000005,"height":32.244003295898438}},{"text":"RenderWrap.jsrb = “puts ‘this is console log’ ”","targetRectangle":{"y":515.96033370494843,"x":150.33403015136719,"width":557.3069999999999,"height":32.244003295898438}},{"text":"RenderWrap.before_html(“name”,“before”)","targetRectangle":{"y":614.96033370494843,"x":150.33403015136719,"width":513.62100000000009,"height":32.244003295898438}},{"text":"RenderWrap.after_html(“name”,“after”)","targetRectangle":{"y":647.96033370494843,"x":150.33403015136719,"width":468.58500000000015,"height":32.244003295898438}},{"text":"Javascript","targetRectangle":{"y":1020.8589935302734,"x":1531.1863632202148,"width":119.5,"height":29.274826049804688}},{"text":"RenderWrap","targetRectangle":{"y":990.35276794433594,"x":873.4129961261749,"width":150.74800000000005,"height":31.245819091796875}},{"text":"html","targetRectangle":{"y":478.4595947265625,"x":1057.0087071533203,"width":64.576000000000022,"height":38.07177734375}}],"baseLayer":{"animations":[],"initialState":{"affineTransform":[1,0,0,1,0,0],"masksToBounds":false,"rotation":0,"scale":1,"position":{"pointX":960,"pointY":540},"width":1920,"sublayerTransform":[1,0,0,0,0,1,0,0,0,0,1,0,0,0,0,1],"contentsRect":{"y":0,"x":0,"width":1,"height":1},"opacity":1,"edgeAntialiasingMask":251658240,"height":1080,"hidden":false,"anchorPoint":{"pointX":0.5,"pointY":0.5}},"objectID":"0","layers":[{"animations":[],"initialState":{"affineTransform":[1,0,0,1,0,0],"masksToBounds":false,"rotation":0,"scale":1,"position":{"pointX":960,"pointY":540},"width":1920,"sublayerTransform":[1,0,0,0,0,1,0,0,0,0,1,-0.00035007912466775983,0,0,0,1],"contentsRect":{"y":0,"x":0,"width":1,"height":1},"opacity":1,"edgeAntialiasingMask":251658240,"height":1080,"hidden":false,"anchorPoint":{"pointX":0.5,"pointY":0.5}},"layers":[{"animations":[],"layers":[],"texturedRectangle":{"isBackgroundTexture":false,"singleTextureOpacity":1,"textureType":0,"textBaseline":0,"textXHeight":0,"isVerticalText":false},"initialState":{"affineTransform":[1,0,0,1,0,0],"masksToBounds":false,"rotation":0,"scale":1,"position":{"pointX":960,"pointY":540},"width":1920,"sublayerTransform":[1,0,0,0,0,1,0,0,0,0,1,0,0,0,0,1],"contentsRect":{"y":0,"x":0,"width":1,"height":1},"opacity":1,"edgeAntialiasingMask":0,"height":1080,"hidden":false,"anchorPoint":{"pointX":0.5,"pointY":0.5}},"texture":"D207410D0EE731715E667FC4EEB89E03"}]}]}}]}